gemfileparser/__init__.py
gemfileparser-0.8.0.dist-info/LICENSE.GPLv3
gemfileparser-0.8.0.dist-info/LICENSE.MIT
gemfileparser-0.8.0.dist-info/METADATA
gemfileparser-0.8.0.dist-info/README.rst
gemfileparser-0.8.0.dist-info/WHEEL
gemfileparser-0.8.0.dist-info/entry_points.txt
gemfileparser-0.8.0.dist-info/top_level.txt
gemfileparser-0.8.0.dist-info/RECORD
