Metadata-Version: 1.1
Name: gemfileparser
Version: 0.8.0
Summary: Parse Ruby Gemfile, .gemspec and Cocoapod .podspec files using Python.
Home-page: https://github.com/gemfileparser/gemfileparser
Author: Balasankar C
Author-email: balasankarc@autistici.org
License: GPL-3.0-or-later OR MIT
Keywords: Ruby Rubygem Gemfile gemspec Cocoapod podspec
Platform: UNKNOWN
Classifier: Development Status :: 5 - Production/Stable
Classifier: Intended Audience :: Developers
Classifier: Operating System :: OS Independent
Classifier: Programming Language :: Python :: 2.7
Classifier: Programming Language :: Python :: 3
Classifier: Programming Language :: Python :: 3.5
Classifier: Programming Language :: Python :: 3.6
Classifier: Programming Language :: Python :: 3.7
Classifier: Programming Language :: Python :: 3.8
Classifier: Topic :: Utilities
